{"version": "1.1.0",
 "packagesDir": ".lake/packages",
 "packages":
 [{"url": "https://github.com/leanprover/doc-gen4",
   "type": "git",
   "subDir": null,
   "scope": "",
   "rev": "f178e492e7f345d7be5a57d2178e95f7a3cc070b",
   "name": "«doc-gen4»",
   "manifestFile": "lake-manifest.json",
   "inputRev": "main",
   "inherited": false,
   "configFile": "lakefile.lean"},
  {"url": "https://github.com/leanprover-community/plausible",
   "type": "git",
   "subDir": null,
   "scope": "",
   "rev": "650d4104daeb660ff3cc46715602a664504e7785",
   "name": "plausible",
   "manifestFile": "lake-manifest.json",
   "inputRev": "main",
   "inherited": false,
   "configFile": "lakefile.toml"},
  {"url": "https://github.com/acmepjz/md4lean",
   "type": "git",
   "subDir": null,
   "scope": "",
   "rev": "6a3fb240133bcb7e1a066fdc784b3fdc304e3fc5",
   "name": "MD4Lean",
   "manifestFile": "lake-manifest.json",
   "inputRev": "main",
   "inherited": false,
   "configFile": "lakefile.lean"},
  {"url": "https://github.com/leanprover/subverso",
   "type": "git",
   "subDir": null,
   "scope": "",
   "rev": "69981335508430ec0fc09241f535aa353c1e978e",
   "name": "subverso",
   "manifestFile": "lake-manifest.json",
   "inputRev": "main",
   "inherited": false,
   "configFile": "lakefile.lean"},
  {"url": "https://github.com/david-christiansen/leansqlite",
   "type": "git",
   "subDir": null,
   "scope": "",
   "rev": "739abe6c8ae0602d6ce56461d33f3e49837c9b70",
   "name": "leansqlite",
   "manifestFile": "lake-manifest.json",
   "inputRev": "main",
   "inherited": true,
   "configFile": "lakefile.lean"},
  {"url": "https://github.com/leanprover/lean4-cli",
   "type": "git",
   "subDir": null,
   "scope": "",
   "rev": "474983579ecce1ca7d8a63e65c7ae0b1a22db6a3",
   "name": "Cli",
   "manifestFile": "lake-manifest.json",
   "inputRev": "main",
   "inherited": true,
   "configFile": "lakefile.toml"},
  {"url": "https://github.com/fgdorais/lean4-unicode-basic",
   "type": "git",
   "subDir": null,
   "scope": "",
   "rev": "9484dd63d30bce157c7f98007a9f26ca4dfb7fb6",
   "name": "UnicodeBasic",
   "manifestFile": "lake-manifest.json",
   "inputRev": "main",
   "inherited": true,
   "configFile": "lakefile.lean"},
  {"url": "https://github.com/dupuisf/BibtexQuery",
   "type": "git",
   "subDir": null,
   "scope": "",
   "rev": "29e7df238aa51dba17463e360e68657a8d433f43",
   "name": "BibtexQuery",
   "manifestFile": "lake-manifest.json",
   "inputRev": "master",
   "inherited": true,
   "configFile": "lakefile.toml"}],
 "name": "verso",
 "lakeDir": ".lake"}
